arrayhascher/README.MD
arrayhascher/__init__.py
arrayhascher/requirements.txt
arrayhascher/thirdparty.json
arrayhascher/xxhash.c
arrayhascher/xxhash.h
arrayhascher-0.11.dist-info/LICENSE.rst
arrayhascher-0.11.dist-info/METADATA
arrayhascher-0.11.dist-info/WHEEL
arrayhascher-0.11.dist-info/top_level.txt
arrayhascher-0.11.dist-info/RECORD
