Metadata-Version: 2.1
Name: arrayhascher
Version: 0.11
Summary: Fast hash in 2D Arrays (Numpy/Pandas/lists/tuples)
Home-page: https://github.com/hansalemaos/arrayhascher
Author: Johannes Fischer
Author-email: aulasparticularesdealemaosp@gmail.com
License: MIT
Keywords: cython,arrays,hash,numpy
Classifier: Development Status :: 4 - Beta
Classifier: Programming Language :: Python :: 3 :: Only
Classifier: Programming Language :: Python :: 3.10
Classifier: Topic :: Software Development :: Libraries :: Python Modules
Classifier: Topic :: Utilities
License-File: LICENSE.rst
Requires-Dist: Cython
Requires-Dist: numpy
Requires-Dist: pandas
